domainpy/__init__.py
domainpy/application/__init__.py
domainpy/application/bus.py
domainpy/application/command.py
domainpy/application/exceptions.py
domainpy/application/handler.py
domainpy/application/integration.py
domainpy/application/projection.py
domainpy/application/projector.py
domainpy/application/query.py
domainpy/application/registry.py
domainpy/application/service.py
domainpy/application/tracer.py
domainpy/application/mappers/__init__.py
domainpy/application/mappers/commandmapper.py
domainpy/application/mappers/eventmapper.py
domainpy/domain/__init__.py
domainpy/domain/exceptions.py
domainpy/domain/repository.py
domainpy/domain/service.py
domainpy/domain/model/__init__.py
domainpy/domain/model/aggregate.py
domainpy/domain/model/entity.py
domainpy/domain/model/event.py
domainpy/domain/model/mutator.py
domainpy/domain/model/specification.py
domainpy/domain/model/value_object.py
domainpy/infrastructure/__init__.py
domainpy/infrastructure/exception.py
domainpy/infrastructure/buses/__init__.py
domainpy/infrastructure/buses/eventbridge.py
domainpy/infrastructure/buses/memory.py
domainpy/infrastructure/buses/sqs.py
domainpy/infrastructure/eventsourced/__init__.py
domainpy/infrastructure/eventsourced/eventstore.py
domainpy/infrastructure/eventsourced/eventstream.py
domainpy/infrastructure/eventsourced/recordmanager.py
domainpy/infrastructure/eventsourced/managers/__init__.py
domainpy/infrastructure/eventsourced/managers/dynamodb.py
domainpy/infrastructure/eventsourced/managers/memory.py
domainpy/infrastructure/projectionsourced/__init__.py
domainpy/infrastructure/projectionsourced/recordmanager.py
domainpy/infrastructure/projectionsourced/managers/__init__.py
domainpy/infrastructure/projectionsourced/managers/memory.py
domainpy/utils/__init__.py
domainpy/utils/bus.py
domainpy/utils/constructable.py
domainpy/utils/dictable.py
domainpy/utils/dynamodb.py
domainpy/utils/immutable.py
domainpy/utils/registry.py
domainpy/utils/subscriber.py
domainpy/utils/traceable.py
domainpy-0.1.22.dist-info/METADATA
domainpy-0.1.22.dist-info/WHEEL
domainpy-0.1.22.dist-info/top_level.txt
domainpy-0.1.22.dist-info/RECORD
