Metadata-Version: 2.1
Name: domainpy
Version: 0.1.22
Summary: A library for DDD, ES, CQRS, TDD + BDD and microservices
Home-page: https://github.com/mymamachef/domainpy
Author: Brian Estrada
Author-email: brianseg014@gmail.com
License: MIT
Download-URL: https://github.com/mymamachef/domainpy/archive/v0.1.22.tar.gz
Keywords: ddd,event sourcing,CQRS
Platform: UNKNOWN
Requires-Dist: boto3 (==1.17.40)
